README.txt
setup.py
jenkins_cffi/__init__.py
jenkins_cffi/build.py
jenkins_cffi/lookup3.c
jenkins_cffi.egg-info/PKG-INFO
jenkins_cffi.egg-info/SOURCES.txt
jenkins_cffi.egg-info/dependency_links.txt
jenkins_cffi.egg-info/requires.txt
jenkins_cffi.egg-info/top_level.txt