Metadata-Version: 1.0
Name: jenkins-cffi
Version: 1.0.2.1
Summary: Python CFFI wrapper around Bob Jenkins' hash functions.
Home-page: https://github.com/what-studio/jenkins-cffi/
Author: Heungsub Lee
Author-email: sub@subl.ee
License: UNKNOWN
Platform: UNKNOWN
